valer.api-1.2.3rc12-nspkg.pth
senaite/api/__init__.py
senaite/api/analysis.py
senaite/api/configure.zcml
senaite/api/docs/API.rst
senaite/api/docs/API_analysis.rst
senaite/api/tests/__init__.py
senaite/api/tests/base.py
senaite/api/tests/test_doctests.py
senaite/api/tests/test_setup.py
valer.api-1.2.3rc12.dist-info/DESCRIPTION.rst
valer.api-1.2.3rc12.dist-info/METADATA
valer.api-1.2.3rc12.dist-info/RECORD
valer.api-1.2.3rc12.dist-info/WHEEL
valer.api-1.2.3rc12.dist-info/entry_points.txt
valer.api-1.2.3rc12.dist-info/metadata.json
valer.api-1.2.3rc12.dist-info/namespace_packages.txt
valer.api-1.2.3rc12.dist-info/top_level.txt
