Metadata-Version: 2.0
Name: valer.api
Version: 1.2.3rc12
Summary: VALER API
Home-page: https://github.com/valeriozhang/senaite.api
Author: Valer Group LLC
Author-email: valerio.zhang@valer.us
License: GPLv2
Platform: UNKNOWN
Classifier: Programming Language :: Python
Classifier: Framework :: Plone
Classifier: Framework :: Zope2
Provides-Extra: test
Requires-Dist: plone.api
Requires-Dist: setuptools
Requires-Dist: valer.core (>=1.3.5rc11)
Provides-Extra: test
Requires-Dist: Products.PloneTestCase; extra == 'test'
Requires-Dist: Products.SecureMailHost; extra == 'test'
Requires-Dist: plone.app.robotframework; extra == 'test'
Requires-Dist: plone.app.testing; extra == 'test'
Requires-Dist: robotframework-debuglibrary; extra == 'test'
Requires-Dist: robotframework-selenium2library; extra == 'test'
Requires-Dist: robotsuite; extra == 'test'
Requires-Dist: unittest2; extra == 'test'
